
{
    "BPM" : 130,
    "MaxBeat" : 8,
    "NoteDelay" : 200,
    "Note"      : [
        {
            "Type" : 1,
            "Length" : 0,
            "SlideTime" : 0,
            "SlideWay"  : 0,
            "RoundTrip" : false,
            "Number"    : 0,
            "Bar"       : 0,
            "Beat"      : 6
        },
        {
            "Type" : 1,
            "Length" : 0,
            "SlideTime" : 0,
            "SlideWay"  : 0,
            "RoundTrip" : false,
            "Number"    : 3,
            "Bar"       : 4,
            "Beat"      : 6
        },
        {
            "Type" : 2,
            "Length" : 31,
            "SlideTime" : 0,
            "SlideWay"  : 0,
            "RoundTrip" : false,
            "Number"    : 5,
            "Bar"       : 8,
            "Beat"      : 2
        },
        {
            "Type" : 1,
            "Length" : 0,
            "SlideTime" : 0,
            "SlideWay"  : 0,
            "RoundTrip" : false,
            "Number"    : 1,
            "Bar"       : 16,
            "Beat"      : 2
        },
        {
            "Type" : 2,
            "Length" : 19,
            "SlideTime" : 0,
            "SlideWay"  : 0,
            "RoundTrip" : false,
            "Number"    : 3,
            "Bar"       : 20,
            "Beat"      : 4
        },
        {
            "Type" : 2,
            "Length" : 15,
            "SlideTime" : 0,
            "SlideWay"  : 0,
            "RoundTrip" : false,
            "Number"    : 0,
            "Bar"       : 25,
            "Beat"      : 4
        },
        {
            "Type" : 1,
            "Length" : 0,
            "SlideTime" : 0,
            "SlideWay"  : 0,
            "RoundTrip" : false,
            "Number"    : 1,
            "Bar"       : 32,
            "Beat"      : 0
        },
        {
            "Type" : 1,
            "Length" : 0,
            "SlideTime" : 0,
            "SlideWay"  : 0,
            "RoundTrip" : false,
            "Number"    : 5,
            "Bar"       : 32,
            "Beat"      : 0
        },
        {
            "Type" : 3,
            "Length" : 2,
            "SlideTime" : 24,
            "SlideWay"  : 1,
            "RoundTrip" : false,
            "Number"    : 1,
            "Bar"       : 40,
            "Beat"      : 0
        },
        {
            "Type" : 1,
            "Length" : 0,
            "SlideTime" : 0,
            "SlideWay"  : 0,
            "RoundTrip" : false,
            "Number"    : 5,
            "Bar"       : 46,
            "Beat"      : 6
        },
        {
            "Type" : 1,
            "Length" : 0,
            "SlideTime" : 0,
            "SlideWay"  : 0,
            "RoundTrip" : false,
            "Number"    : 1,
            "Bar"       : 47,
            "Beat"      : 6
        },
        {
            "Type" : 2,
            "Length" : 31,
            "SlideTime" : 0,
            "SlideWay"  : 0,
            "RoundTrip" : false,
            "Number"    : 3,
            "Bar"       : 52,
            "Beat"      : 2
        },
        {
            "Type" : 1,
            "Length" : 0,
            "SlideTime" : 0,
            "SlideWay"  : 0,
            "RoundTrip" : false,
            "Number"    : 4,
            "Bar"       : 59,
            "Beat"      : 2
        },
        {
            "Type" : 1,
            "Length" : 0,
            "SlideTime" : 0,
            "SlideWay"  : 0,
            "RoundTrip" : false,
            "Number"    : 1,
            "Bar"       : 63,
            "Beat"      : 6
        },
        {
            "Type" : 1,
            "Length" : 0,
            "SlideTime" : 0,
            "SlideWay"  : 0,
            "RoundTrip" : false,
            "Number"    : 2,
            "Bar"       : 65,
            "Beat"      : 0
        },
        {
            "Type" : 1,
            "Length" : 0,
            "SlideTime" : 0,
            "SlideWay"  : 0,
            "RoundTrip" : false,
            "Number"    : 5,
            "Bar"       : 67,
            "Beat"      : 6
        },
        {
            "Type" : 1,
            "Length" : 0,
            "SlideTime" : 0,
            "SlideWay"  : 0,
            "RoundTrip" : false,
            "Number"    : 4,
            "Bar"       : 69,
            "Beat"      : 0
        },
        {
            "Type" : 2,
            "Length" : 31,
            "SlideTime" : 0,
            "SlideWay"  : 0,
            "RoundTrip" : false,
            "Number"    : 0,
            "Bar"       : 71,
            "Beat"      : 4
        },
        {
            "Type" : 1,
            "Length" : 0,
            "SlideTime" : 0,
            "SlideWay"  : 0,
            "RoundTrip" : false,
            "Number"    : 2,
            "Bar"       : 79,
            "Beat"      : 4
        },
        {
            "Type" : 1,
            "Length" : 0,
            "SlideTime" : 0,
            "SlideWay"  : 0,
            "RoundTrip" : false,
            "Number"    : 4,
            "Bar"       : 79,
            "Beat"      : 4
        },
        {
            "Type" : 2,
            "Length" : 15,
            "SlideTime" : 0,
            "SlideWay"  : 0,
            "RoundTrip" : false,
            "Number"    : 5,
            "Bar"       : 83,
            "Beat"      : 4
        },
        {
            "Type" : 1,
            "Length" : 0,
            "SlideTime" : 0,
            "SlideWay"  : 0,
            "RoundTrip" : false,
            "Number"    : 1,
            "Bar"       : 88,
            "Beat"      : 0
        },
        {
            "Type" : 1,
            "Length" : 0,
            "SlideTime" : 0,
            "SlideWay"  : 0,
            "RoundTrip" : false,
            "Number"    : 4,
            "Bar"       : 88,
            "Beat"      : 4
        },
        {
            "Type" : 1,
            "Length" : 0,
            "SlideTime" : 0,
            "SlideWay"  : 0,
            "RoundTrip" : false,
            "Number"    : 5,
            "Bar"       : 90,
            "Beat"      : 0
        },
        {
            "Type" : 1,
            "Length" : 0,
            "SlideTime" : 0,
            "SlideWay"  : 0,
            "RoundTrip" : false,
            "Number"    : 2,
            "Bar"       : 90,
            "Beat"      : 4
        },
        {
            "Type" : 3,
            "Length" : 2,
            "SlideTime" : 47,
            "SlideWay"  : 1,
            "RoundTrip" : false,
            "Number"    : 0,
            "Bar"       : 95,
            "Beat"      : 2
        },
        {
            "Type" : 3,
            "Length" : 2,
            "SlideTime" : 47,
            "SlideWay"  : 1,
            "RoundTrip" : false,
            "Number"    : 3,
            "Bar"       : 103,
            "Beat"      : 2
        },
        {
            "Type" : 2,
            "Length" : 39,
            "SlideTime" : 0,
            "SlideWay"  : 0,
            "RoundTrip" : false,
            "Number"    : 0,
            "Bar"       : 112,
            "Beat"      : 0
        },
        {
            "Type" : 1,
            "Length" : 0,
            "SlideTime" : 0,
            "SlideWay"  : 0,
            "RoundTrip" : false,
            "Number"    : 4,
            "Bar"       : 119,
            "Beat"      : 4
        },
        {
            "Type" : 1,
            "Length" : 0,
            "SlideTime" : 0,
            "SlideWay"  : 0,
            "RoundTrip" : false,
            "Number"    : 2,
            "Bar"       : 121,
            "Beat"      : 4
        },
        {
            "Type" : 3,
            "Length" : 2,
            "SlideTime" : 47,
            "SlideWay"  : 0,
            "RoundTrip" : false,
            "Number"    : 0,
            "Bar"       : 127,
            "Beat"      : 2
        },
        {
            "Type" : 3,
            "Length" : 2,
            "SlideTime" : 47,
            "SlideWay"  : 0,
            "RoundTrip" : false,
            "Number"    : 3,
            "Bar"       : 135,
            "Beat"      : 2
        },
        {
            "Type" : 2,
            "Length" : 39,
            "SlideTime" : 0,
            "SlideWay"  : 0,
            "RoundTrip" : false,
            "Number"    : 3,
            "Bar"       : 143,
            "Beat"      : 6
        },
        {
            "Type" : 1,
            "Length" : 0,
            "SlideTime" : 0,
            "SlideWay"  : 0,
            "RoundTrip" : false,
            "Number"    : 0,
            "Bar"       : 151,
            "Beat"      : 0
        },
        {
            "Type" : 1,
            "Length" : 0,
            "SlideTime" : 0,
            "SlideWay"  : 0,
            "RoundTrip" : false,
            "Number"    : 3,
            "Bar"       : 153,
            "Beat"      : 0
        },
        {
            "Type" : 4,
            "Length" : 0,
            "SlideTime" : 0,
            "SlideWay"  : 0,
            "RoundTrip" : false,
            "Number"    : 0,
            "Bar"       : 159,
            "Beat"      : 1
        },
        {
            "Type" : 2,
            "Length" : 15,
            "SlideTime" : 0,
            "SlideWay"  : 0,
            "RoundTrip" : false,
            "Number"    : 1,
            "Bar"       : 163,
            "Beat"      : 0
        },
        {
            "Type" : 2,
            "Length" : 15,
            "SlideTime" : 0,
            "SlideWay"  : 0,
            "RoundTrip" : false,
            "Number"    : 4,
            "Bar"       : 167,
            "Beat"      : 0
        },
        {
            "Type" : 4,
            "Length" : 0,
            "SlideTime" : 0,
            "SlideWay"  : 0,
            "RoundTrip" : false,
            "Number"    : 0,
            "Bar"       : 175,
            "Beat"      : 0
        },
        {
            "Type" : 1,
            "Length" : 0,
            "SlideTime" : 0,
            "SlideWay"  : 0,
            "RoundTrip" : false,
            "Number"    : 4,
            "Bar"       : 184,
            "Beat"      : 0
        },
        {
            "Type" : 2,
            "Length" : 47,
            "SlideTime" : 0,
            "SlideWay"  : 0,
            "RoundTrip" : false,
            "Number"    : 2,
            "Bar"       : 187,
            "Beat"      : 0
        }
    ]
}